mcc/__init__.py
mcc/__main__.py
mcc/cldcnct.py
mcc/colors.py
mcc/confdir.py
mcc/config.ini
mcc/core.py
mcc/tables.py
mcc/uimode.py
mcc-0.9.8.dist-info/METADATA
mcc-0.9.8.dist-info/RECORD
mcc-0.9.8.dist-info/WHEEL
mcc-0.9.8.dist-info/entry_points.txt
mcc-0.9.8.dist-info/top_level.txt
